{
  "materials": [
    {
      "id": "3a95313a6c21",
      "title": "坚持不懈的力量",
      "content": "古人云：'绳锯木断，水滴石穿。'这句话告诉我们，持续不断的努力具有巨大的力量。无论是学习还是工作，只要我们坚持不懈，终将收获成功。就像著名科学家爱迪生发明电灯泡，经历了上千次失败，但他从未放弃，最终照亮了整个世界。",
      "category": "名言警句",
      "keywords": [
        "坚持",
        "毅力",
        "成功",
        "努力"
      ],
      "source": "古代名言",
      "difficulty_level": "middle"
    },
    {
      "id": "3d969b1e37d1",
      "title": "友谊的珍贵",
      "content": "真正的友谊如同珍珠一样珍贵。朋友在我们快乐时与我们分享喜悦，在我们困难时给予帮助和支持。马克思和恩格斯的友谊就是最好的例子，他们在学术上相互切磋，在生活中相互扶持，这种友谊超越了时间和空间的限制。",
      "category": "情感表达",
      "keywords": [
        "友谊",
        "朋友",
        "支持",
        "分享"
      ],
      "source": "现代素材",
      "difficulty_level": "middle"
    },
    {
      "id": "f03858f3e93e",
      "title": "环保的重要性",
      "content": "地球是我们共同的家园，保护环境是每个人的责任。随着工业的发展，环境污染日益严重，我们必须采取行动。从小事做起，比如垃圾分类、节约用水、减少使用塑料袋等，每个人的小小努力汇聚起来就能产生巨大的力量。",
      "category": "社会话题",
      "keywords": [
        "环保",
        "责任",
        "行动",
        "家园"
      ],
      "source": "时事素材",
      "difficulty_level": "high"
    },
    {
      "id": "cc3674415840",
      "title": "读书的意义",
      "content": "书籍是人类进步的阶梯。通过读书，我们可以获得知识，开阔视野，提升思维能力。读书不仅能让我们了解世界，更能让我们了解自己。正如莎士比亚所说：'书籍是全世界的营养品。'让我们在书的海洋中尽情遨游吧。",
      "category": "学习成长",
      "keywords": [
        "读书",
        "知识",
        "成长",
        "智慧"
      ],
      "source": "教育名言",
      "difficulty_level": "middle"
    },
    {
      "id": "8cc53eec391e",
      "title": "坚持不懈的力量",
      "content": "古人云：'绳锯木断，水滴石穿。'这句话告诉我们，持续不断的努力具有巨大的力量。无论是学习还是工作，只要我们坚持不懈，终将收获成功。就像著名科学家爱迪生发明电灯泡，经历了上千次失败，但他从未放弃，最终照亮了整个世界。",
      "category": "名言警句",
      "difficulty_level": "middle",
      "keywords": [
        "坚持",
        "毅力",
        "成功",
        "努力"
      ]
    },
    {
      "id": "31a0cb8c7a97",
      "title": "友谊的珍贵",
      "content": "真正的友谊如同珍珠一样珍贵。朋友在我们快乐时与我们分享喜悦，在我们困难时给予帮助和支持。马克思和恩格斯的友谊就是最好的例子，他们在学术上相互切磋，在生活中相互扶持，这种友谊超越了时间和空间的限制。",
      "category": "情感表达",
      "difficulty_level": "middle",
      "keywords": [
        "友谊",
        "朋友",
        "支持",
        "分享"
      ]
    },
    {
      "id": "c2d4431ff1c8",
      "title": "读书的意义",
      "content": "书籍是人类进步的阶梯。通过读书，我们可以获得知识，开阔视野，提升思维能力。读书不仅能让我们了解世界，更能让我们了解自己。正如莎士比亚所说：'书籍是全世界的营养品。'让我们在书的海洋中尽情遨游吧。",
      "category": "学习成长",
      "difficulty_level": "middle",
      "keywords": [
        "读书",
        "知识",
        "成长",
        "智慧"
      ]
    },
    {
      "id": "6344aedf5650",
      "title": "坚持不懈的力量",
      "content": "古人云：'绳锯木断，水滴石穿。'这句话告诉我们，持续不断的努力具有巨大的力量。无论是学习还是工作，只要我们坚持不懈，终将收获成功。就像著名科学家爱迪生发明电灯泡，经历了上千次失败，但他从未放弃，最终照亮了整个世界。",
      "category": "名言警句",
      "difficulty_level": "middle",
      "keywords": [
        "坚持",
        "毅力",
        "成功",
        "努力"
      ]
    },
    {
      "id": "443c1e1e1f8e",
      "title": "友谊的珍贵",
      "content": "真正的友谊如同珍珠一样珍贵。朋友在我们快乐时与我们分享喜悦，在我们困难时给予帮助和支持。马克思和恩格斯的友谊就是最好的例子，他们在学术上相互切磋，在生活中相互扶持，这种友谊超越了时间和空间的限制。",
      "category": "情感表达",
      "difficulty_level": "middle",
      "keywords": [
        "友谊",
        "朋友",
        "支持",
        "分享"
      ]
    },
    {
      "id": "2659c3977dea",
      "title": "读书的意义",
      "content": "书籍是人类进步的阶梯。通过读书，我们可以获得知识，开阔视野，提升思维能力。读书不仅能让我们了解世界，更能让我们了解自己。正如莎士比亚所说：'书籍是全世界的营养品。'让我们在书的海洋中尽情遨游吧。",
      "category": "学习成长",
      "difficulty_level": "middle",
      "keywords": [
        "读书",
        "知识",
        "成长",
        "智慧"
      ]
    },
    {
      "id": "ab130c195907",
      "title": "坚持不懈的力量",
      "content": "古人云：'绳锯木断，水滴石穿。'这句话告诉我们，持续不断的努力具有巨大的力量。无论是学习还是工作，只要我们坚持不懈，终将收获成功。就像著名科学家爱迪生发明电灯泡，经历了上千次失败，但他从未放弃，最终照亮了整个世界。",
      "category": "名言警句",
      "difficulty_level": "middle",
      "keywords": [
        "坚持",
        "毅力",
        "成功",
        "努力"
      ]
    },
    {
      "id": "7230a65d0c7c",
      "title": "友谊的珍贵",
      "content": "真正的友谊如同珍珠一样珍贵。朋友在我们快乐时与我们分享喜悦，在我们困难时给予帮助和支持。马克思和恩格斯的友谊就是最好的例子，他们在学术上相互切磋，在生活中相互扶持，这种友谊超越了时间和空间的限制。",
      "category": "情感表达",
      "difficulty_level": "middle",
      "keywords": [
        "友谊",
        "朋友",
        "支持",
        "分享"
      ]
    },
    {
      "id": "fdecc4169436",
      "title": "读书的意义",
      "content": "书籍是人类进步的阶梯。通过读书，我们可以获得知识，开阔视野，提升思维能力。读书不仅能让我们了解世界，更能让我们了解自己。正如莎士比亚所说：'书籍是全世界的营养品。'让我们在书的海洋中尽情遨游吧。",
      "category": "学习成长",
      "difficulty_level": "middle",
      "keywords": [
        "读书",
        "知识",
        "成长",
        "智慧"
      ]
    },
    {
      "id": "d59b2edd47fa",
      "title": "坚持不懈的力量",
      "content": "古人云：'绳锯木断，水滴石穿。'这句话告诉我们，持续不断的努力具有巨大的力量。无论是学习还是工作，只要我们坚持不懈，终将收获成功。就像著名科学家爱迪生发明电灯泡，经历了上千次失败，但他从未放弃，最终照亮了整个世界。",
      "category": "名言警句",
      "difficulty_level": "middle",
      "keywords": [
        "坚持",
        "毅力",
        "成功",
        "努力"
      ]
    },
    {
      "id": "cb61b3ceb413",
      "title": "友谊的珍贵",
      "content": "真正的友谊如同珍珠一样珍贵。朋友在我们快乐时与我们分享喜悦，在我们困难时给予帮助和支持。马克思和恩格斯的友谊就是最好的例子，他们在学术上相互切磋，在生活中相互扶持，这种友谊超越了时间和空间的限制。",
      "category": "情感表达",
      "difficulty_level": "middle",
      "keywords": [
        "友谊",
        "朋友",
        "支持",
        "分享"
      ]
    },
    {
      "id": "43b6cded84fe",
      "title": "读书的意义",
      "content": "书籍是人类进步的阶梯。通过读书，我们可以获得知识，开阔视野，提升思维能力。读书不仅能让我们了解世界，更能让我们了解自己。正如莎士比亚所说：'书籍是全世界的营养品。'让我们在书的海洋中尽情遨游吧。",
      "category": "学习成长",
      "difficulty_level": "middle",
      "keywords": [
        "读书",
        "知识",
        "成长",
        "智慧"
      ]
    },
    {
      "id": "e76d18e44711",
      "title": "坚持不懈的力量",
      "content": "古人云：'绳锯木断，水滴石穿。'这句话告诉我们，持续不断的努力具有巨大的力量。无论是学习还是工作，只要我们坚持不懈，终将收获成功。就像著名科学家爱迪生发明电灯泡，经历了上千次失败，但他从未放弃，最终照亮了整个世界。",
      "category": "名言警句",
      "difficulty_level": "middle",
      "keywords": [
        "坚持",
        "毅力",
        "成功",
        "努力"
      ]
    },
    {
      "id": "1f29f28b0e69",
      "title": "友谊的珍贵",
      "content": "真正的友谊如同珍珠一样珍贵。朋友在我们快乐时与我们分享喜悦，在我们困难时给予帮助和支持。马克思和恩格斯的友谊就是最好的例子，他们在学术上相互切磋，在生活中相互扶持，这种友谊超越了时间和空间的限制。",
      "category": "情感表达",
      "difficulty_level": "middle",
      "keywords": [
        "友谊",
        "朋友",
        "支持",
        "分享"
      ]
    },
    {
      "id": "ab1c2354ef62",
      "title": "读书的意义",
      "content": "书籍是人类进步的阶梯。通过读书，我们可以获得知识，开阔视野，提升思维能力。读书不仅能让我们了解世界，更能让我们了解自己。正如莎士比亚所说：'书籍是全世界的营养品。'让我们在书的海洋中尽情遨游吧。",
      "category": "学习成长",
      "difficulty_level": "middle",
      "keywords": [
        "读书",
        "知识",
        "成长",
        "智慧"
      ]
    },
    {
      "id": "192bc9c49c64",
      "title": "坚持不懈的力量",
      "content": "古人云：'绳锯木断，水滴石穿。'这句话告诉我们，持续不断的努力具有巨大的力量。无论是学习还是工作，只要我们坚持不懈，终将收获成功。就像著名科学家爱迪生发明电灯泡，经历了上千次失败，但他从未放弃，最终照亮了整个世界。",
      "category": "名言警句",
      "difficulty_level": "middle",
      "keywords": [
        "坚持",
        "毅力",
        "成功",
        "努力"
      ]
    },
    {
      "id": "80853c468ca3",
      "title": "友谊的珍贵",
      "content": "真正的友谊如同珍珠一样珍贵。朋友在我们快乐时与我们分享喜悦，在我们困难时给予帮助和支持。马克思和恩格斯的友谊就是最好的例子，他们在学术上相互切磋，在生活中相互扶持，这种友谊超越了时间和空间的限制。",
      "category": "情感表达",
      "difficulty_level": "middle",
      "keywords": [
        "友谊",
        "朋友",
        "支持",
        "分享"
      ]
    },
    {
      "id": "fbe46e39749c",
      "title": "读书的意义",
      "content": "书籍是人类进步的阶梯。通过读书，我们可以获得知识，开阔视野，提升思维能力。读书不仅能让我们了解世界，更能让我们了解自己。正如莎士比亚所说：'书籍是全世界的营养品。'让我们在书的海洋中尽情遨游吧。",
      "category": "学习成长",
      "difficulty_level": "middle",
      "keywords": [
        "读书",
        "知识",
        "成长",
        "智慧"
      ]
    },
    {
      "id": "c0b1b02cd011",
      "title": "坚持不懈的力量",
      "content": "古人云：'绳锯木断，水滴石穿。'这句话告诉我们，持续不断的努力具有巨大的力量。无论是学习还是工作，只要我们坚持不懈，终将收获成功。就像著名科学家爱迪生发明电灯泡，经历了上千次失败，但他从未放弃，最终照亮了整个世界。",
      "category": "名言警句",
      "difficulty_level": "middle",
      "keywords": [
        "坚持",
        "毅力",
        "成功",
        "努力"
      ]
    },
    {
      "id": "fc492cbc1c65",
      "title": "友谊的珍贵",
      "content": "真正的友谊如同珍珠一样珍贵。朋友在我们快乐时与我们分享喜悦，在我们困难时给予帮助和支持。马克思和恩格斯的友谊就是最好的例子，他们在学术上相互切磋，在生活中相互扶持，这种友谊超越了时间和空间的限制。",
      "category": "情感表达",
      "difficulty_level": "middle",
      "keywords": [
        "友谊",
        "朋友",
        "支持",
        "分享"
      ]
    },
    {
      "id": "8d59faac5b78",
      "title": "读书的意义",
      "content": "书籍是人类进步的阶梯。通过读书，我们可以获得知识，开阔视野，提升思维能力。读书不仅能让我们了解世界，更能让我们了解自己。正如莎士比亚所说：'书籍是全世界的营养品。'让我们在书的海洋中尽情遨游吧。",
      "category": "学习成长",
      "difficulty_level": "middle",
      "keywords": [
        "读书",
        "知识",
        "成长",
        "智慧"
      ]
    },
    {
      "id": "2e30031ec623",
      "title": "坚持不懈的力量",
      "content": "古人云：'绳锯木断，水滴石穿。'这句话告诉我们，持续不断的努力具有巨大的力量。无论是学习还是工作，只要我们坚持不懈，终将收获成功。就像著名科学家爱迪生发明电灯泡，经历了上千次失败，但他从未放弃，最终照亮了整个世界。",
      "category": "名言警句",
      "difficulty_level": "middle",
      "keywords": [
        "坚持",
        "毅力",
        "成功",
        "努力"
      ]
    },
    {
      "id": "bf96fd383686",
      "title": "友谊的珍贵",
      "content": "真正的友谊如同珍珠一样珍贵。朋友在我们快乐时与我们分享喜悦，在我们困难时给予帮助和支持。马克思和恩格斯的友谊就是最好的例子，他们在学术上相互切磋，在生活中相互扶持，这种友谊超越了时间和空间的限制。",
      "category": "情感表达",
      "difficulty_level": "middle",
      "keywords": [
        "友谊",
        "朋友",
        "支持",
        "分享"
      ]
    },
    {
      "id": "51a7657f2f85",
      "title": "读书的意义",
      "content": "书籍是人类进步的阶梯。通过读书，我们可以获得知识，开阔视野，提升思维能力。读书不仅能让我们了解世界，更能让我们了解自己。正如莎士比亚所说：'书籍是全世界的营养品。'让我们在书的海洋中尽情遨游吧。",
      "category": "学习成长",
      "difficulty_level": "middle",
      "keywords": [
        "读书",
        "知识",
        "成长",
        "智慧"
      ]
    },
    {
      "id": "46473bb61491",
      "title": "坚持不懈的力量",
      "content": "古人云：'绳锯木断，水滴石穿。'这句话告诉我们，持续不断的努力具有巨大的力量。无论是学习还是工作，只要我们坚持不懈，终将收获成功。就像著名科学家爱迪生发明电灯泡，经历了上千次失败，但他从未放弃，最终照亮了整个世界。",
      "category": "名言警句",
      "difficulty_level": "middle",
      "keywords": [
        "坚持",
        "毅力",
        "成功",
        "努力"
      ]
    },
    {
      "id": "b5f74cd777f6",
      "title": "友谊的珍贵",
      "content": "真正的友谊如同珍珠一样珍贵。朋友在我们快乐时与我们分享喜悦，在我们困难时给予帮助和支持。马克思和恩格斯的友谊就是最好的例子，他们在学术上相互切磋，在生活中相互扶持，这种友谊超越了时间和空间的限制。",
      "category": "情感表达",
      "difficulty_level": "middle",
      "keywords": [
        "友谊",
        "朋友",
        "支持",
        "分享"
      ]
    },
    {
      "id": "d4e0338b9138",
      "title": "读书的意义",
      "content": "书籍是人类进步的阶梯。通过读书，我们可以获得知识，开阔视野，提升思维能力。读书不仅能让我们了解世界，更能让我们了解自己。正如莎士比亚所说：'书籍是全世界的营养品。'让我们在书的海洋中尽情遨游吧。",
      "category": "学习成长",
      "difficulty_level": "middle",
      "keywords": [
        "读书",
        "知识",
        "成长",
        "智慧"
      ]
    }
  ]
}